pageplot/__init__.py
pageplot/config.py
pageplot/configextension.py
pageplot/exceptions.py
pageplot/extensionmodel.py
pageplot/mask.py
pageplot/plotcontainer.py
pageplot/plotmodel.py
pageplot/runner.py
pageplot/validators.py
pageplot/extensions/__init__.py
pageplot/extensions/axes_limits.py
pageplot/extensions/legend.py
pageplot/extensions/mass_function.py
pageplot/extensions/mean_line.py
pageplot/extensions/median_line.py
pageplot/extensions/metadata.py
pageplot/extensions/scale_axes.py
pageplot/extensions/scatter.py
pageplot/extensions/two_dimensional_histogram.py
pageplot/extensions/velociraptor_data.py
pageplot/io/__init__.py
pageplot/io/areposubfind.py
pageplot/io/h5py.py
pageplot/io/multi.py
pageplot/io/spec.py
pageplot/webpage/__init__.py
pageplot/webpage/html.py
pageplot-0.0.2.dist-info/LICENSE
pageplot-0.0.2.dist-info/METADATA
pageplot-0.0.2.dist-info/WHEEL
pageplot-0.0.2.dist-info/top_level.txt
pageplot-0.0.2.dist-info/RECORD
