Metadata-Version: 2.1
Name: pageplot
Version: 0.0.2
Summary: UNKNOWN
Home-page: UNKNOWN
Author: Josh Borrow
Author-email: josh@joshborrow.com
License: UNKNOWN
Platform: UNKNOWN
Classifier: Programming Language :: Python :: 3.9
Classifier: License :: OSI Approved :: MIT License
Classifier: Operating System :: OS Independent
License-File: LICENSE
Requires-Dist: attrs
Requires-Dist: h5py
Requires-Dist: velociraptor
Requires-Dist: matplotlib
Requires-Dist: numpy
Requires-Dist: scipy
Requires-Dist: unyt
